{"name":"Story: Classic 08","conf":{"id":"root","version":2,"artboards":[{"type":"artboard","x":0,"y":0,"width":1080,"height":1920,"angle":0,"scale":1,"opacity":100,"color":"#ffffff","duration":4000,"layers":[{"type":"image","url":"userAsset:3d573839-b8a3-4c97-af5e-aec02d5bace2.jpg","mediaName":"eugene-golovesov-pFYgz1Sb21c-unsplash.jpg","width":1080,"height":840,"x":0,"y":0,"cornerRadius":0,"angle":0,"scale":1,"opacity":100,"id":"TSRWg3Tq"},{"type":"image","url":"userAsset:5cc0cfa2-1aa8-43cd-934e-9148a3f6daed.jpg","mediaName":"eugene-golovesov-TGQdhguyICg-unsplash.jpg","width":480,"height":480,"x":40,"y":880,"cornerRadius":0,"angle":0,"scale":1,"opacity":100,"id":"TQW4lNRi"},{"type":"image","url":"userAsset:b24ee015-4ffd-492b-9dca-4a2b4950a214.jpg","mediaName":"eugene-golovesov-TGQdhguyICg-unsplash.jpg","width":480,"height":480,"x":560,"y":1400,"cornerRadius":0,"angle":0,"scale":1,"opacity":100,"id":"dnJ59Q4X"},{"type":"image","url":"userAsset:1a1940fd-490c-453b-acae-f9ef009c1226.jpg","mediaName":"eugene-golovesov-FQ2Bx0e9zdk-unsplash.jpg","width":480,"height":480,"x":560,"y":880,"cornerRadius":0,"angle":0,"scale":1,"opacity":100,"id":"8WQbzu7N"},{"type":"image","url":"userAsset:8def4891-f70e-4b7f-851e-8f395842ebc8.jpg","mediaName":"eugene-golovesov-FQ2Bx0e9zdk-unsplash.jpg","width":480,"height":480,"x":40,"y":1400,"cornerRadius":0,"angle":0,"scale":1,"opacity":100,"id":"y7Fupphd"}],"operations":[{"direction":"down","zoomContent":true,"easing":"natural","type":"maskRevealIn","startTime":0,"targetId":"TSRWg3Tq","id":"FnOwfMWE","endTime":800},{"maskSize":90,"zoomContent":true,"easing":"natural","type":"maskExpandIn","startTime":0,"targetId":"TQW4lNRi","id":"TKZLB4mG","endTime":800},{"maskSize":90,"zoomContent":true,"easing":"natural","type":"maskExpandIn","startTime":0,"targetId":"8WQbzu7N","id":"sop8xGCv","endTime":800},{"maskSize":90,"zoomContent":true,"easing":"natural","type":"maskExpandIn","startTime":0,"targetId":"y7Fupphd","id":"DxlmG4UV","endTime":800},{"maskSize":90,"zoomContent":true,"easing":"natural","type":"maskExpandIn","startTime":0,"targetId":"dnJ59Q4X","id":"pvKITtmn","endTime":800},{"easing":"natural","type":"maskRevealOut","startTime":3400,"targetId":"TSRWg3Tq","id":"keomBpC7","endTime":3800,"direction":"up","zoomContent":true},{"easing":"natural","type":"maskShrinkOut","startTime":3450,"targetId":"TQW4lNRi","id":"qL6ns7by","endTime":3850,"maskSize":90,"zoomContent":true},{"easing":"natural","type":"maskShrinkOut","startTime":3450,"targetId":"8WQbzu7N","id":"fP6aHbM5","endTime":3850,"maskSize":90,"zoomContent":true},{"easing":"natural","type":"maskShrinkOut","startTime":3450,"targetId":"y7Fupphd","id":"DrnSCF4L","endTime":3850,"maskSize":90,"zoomContent":true},{"easing":"natural","type":"maskShrinkOut","startTime":3450,"targetId":"dnJ59Q4X","id":"cmDIVdOD","endTime":3850,"maskSize":90,"zoomContent":true}],"id":"OL8H3gaf"}]},"syncedAt":"2021-05-19T15:18:15.701Z","createdAt":"2021-05-19T15:08:45.148Z"}