{"name":"Cross background","conf":{"id":"root","version":4,"artboards":[{"type":"artboard","x":0,"y":0,"width":1920,"height":1080,"angle":0,"scale":1,"opacity":100,"background":true,"fillColor":"#ff4d6d","duration":1000,"layers":[{"layers":[{"id":"UStNWFvS","type":"svg","url":"userAsset:d53cb250-dc2d-4d22-a159-5ab4a8fd2d6d.svg","mediaName":"Cross.svg","width":40,"height":40,"x":0,"y":800,"angle":0,"scale":1,"opacity":100,"svgfill":"#ffb3c1"},{"id":"GoTxxbny","type":"svg","url":"userAsset:d53cb250-dc2d-4d22-a159-5ab4a8fd2d6d.svg","mediaName":"Cross.svg","width":40,"height":40,"x":0,"y":600,"angle":0,"scale":1,"opacity":100,"svgfill":"#ffb3c1"},{"id":"9GiNZPUd","type":"svg","url":"userAsset:d53cb250-dc2d-4d22-a159-5ab4a8fd2d6d.svg","mediaName":"Cross.svg","width":40,"height":40,"x":0,"y":400,"angle":0,"scale":1,"opacity":100,"svgfill":"#ffb3c1"},{"id":"yoTD10dT","type":"svg","url":"userAsset:d53cb250-dc2d-4d22-a159-5ab4a8fd2d6d.svg","mediaName":"Cross.svg","width":40,"height":40,"x":0,"y":200,"angle":0,"scale":1,"opacity":100,"svgfill":"#ffb3c1"},{"id":"M9954U3h","type":"svg","url":"userAsset:d53cb250-dc2d-4d22-a159-5ab4a8fd2d6d.svg","mediaName":"Cross.svg","width":40,"height":40,"x":0,"y":0,"angle":0,"scale":1,"opacity":100,"svgfill":"#ffb3c1"}],"scale":1,"angle":0,"opacity":100,"id":"rblWQgxK","type":"layerGrp","x":137,"y":117,"width":40,"height":840,"cornerRadius":0,"name":"Column"},{"layers":[{"id":"JJf0eJuX","type":"svg","url":"userAsset:d53cb250-dc2d-4d22-a159-5ab4a8fd2d6d.svg","mediaName":"Cross.svg","width":40,"height":40,"x":0,"y":1000,"angle":0,"scale":1,"opacity":100,"svgfill":"#ffb3c1"},{"id":"1iPM8VNE","type":"svg","url":"userAsset:d53cb250-dc2d-4d22-a159-5ab4a8fd2d6d.svg","mediaName":"Cross.svg","width":40,"height":40,"x":0,"y":800,"angle":0,"scale":1,"opacity":100,"svgfill":"#ffb3c1"},{"id":"RTsD9U3M","type":"svg","url":"userAsset:d53cb250-dc2d-4d22-a159-5ab4a8fd2d6d.svg","mediaName":"Cross.svg","width":40,"height":40,"x":0,"y":600,"angle":0,"scale":1,"opacity":100,"svgfill":"#ffb3c1"},{"id":"kp6Gwzr1","type":"svg","url":"userAsset:d53cb250-dc2d-4d22-a159-5ab4a8fd2d6d.svg","mediaName":"Cross.svg","width":40,"height":40,"x":0,"y":400,"angle":0,"scale":1,"opacity":100,"svgfill":"#ffb3c1"},{"id":"UzrRmrOF","type":"svg","url":"userAsset:d53cb250-dc2d-4d22-a159-5ab4a8fd2d6d.svg","mediaName":"Cross.svg","width":40,"height":40,"x":0,"y":200,"angle":0,"scale":1,"opacity":100,"svgfill":"#ffb3c1"},{"id":"Sb0Zbd4M","type":"svg","url":"userAsset:d53cb250-dc2d-4d22-a159-5ab4a8fd2d6d.svg","mediaName":"Cross.svg","width":40,"height":40,"x":0,"y":0,"angle":0,"scale":1,"opacity":100,"svgfill":"#ffb3c1"}],"scale":1,"angle":0,"opacity":100,"id":"NvLDNZTG","type":"layerGrp","x":337.70418752336514,"y":16.99380148281432,"width":40,"height":1040,"cornerRadius":0,"name":"Column"},{"layers":[{"id":"uB929Uzz","type":"svg","url":"userAsset:d53cb250-dc2d-4d22-a159-5ab4a8fd2d6d.svg","mediaName":"Cross.svg","width":40,"height":40,"x":0,"y":800,"angle":0,"scale":1,"opacity":100,"svgfill":"#ffb3c1"},{"id":"kzsRoRVd","type":"svg","url":"userAsset:d53cb250-dc2d-4d22-a159-5ab4a8fd2d6d.svg","mediaName":"Cross.svg","width":40,"height":40,"x":0,"y":600,"angle":0,"scale":1,"opacity":100,"svgfill":"#ffb3c1"},{"id":"XVffq7KK","type":"svg","url":"userAsset:d53cb250-dc2d-4d22-a159-5ab4a8fd2d6d.svg","mediaName":"Cross.svg","width":40,"height":40,"x":0,"y":400,"angle":0,"scale":1,"opacity":100,"svgfill":"#ffb3c1"},{"id":"WLOx6oU2","type":"svg","url":"userAsset:d53cb250-dc2d-4d22-a159-5ab4a8fd2d6d.svg","mediaName":"Cross.svg","width":40,"height":40,"x":0,"y":200,"angle":0,"scale":1,"opacity":100,"svgfill":"#ffb3c1"},{"id":"H0qoSgAF","type":"svg","url":"userAsset:d53cb250-dc2d-4d22-a159-5ab4a8fd2d6d.svg","mediaName":"Cross.svg","width":40,"height":40,"x":0,"y":0,"angle":0,"scale":1,"opacity":100,"svgfill":"#ffb3c1"}],"scale":1,"angle":0,"opacity":100,"id":"pSr4NES5","type":"layerGrp","x":537.6675271097283,"y":112.79913268818612,"width":40,"height":840,"cornerRadius":0,"name":"Column"},{"layers":[{"id":"VF9i6mBw","type":"svg","url":"userAsset:d53cb250-dc2d-4d22-a159-5ab4a8fd2d6d.svg","mediaName":"Cross.svg","width":40,"height":40,"x":0,"y":1000,"angle":0,"scale":1,"opacity":100,"svgfill":"#ffb3c1"},{"id":"c3D5rgI3","type":"svg","url":"userAsset:d53cb250-dc2d-4d22-a159-5ab4a8fd2d6d.svg","mediaName":"Cross.svg","width":40,"height":40,"x":0,"y":800,"angle":0,"scale":1,"opacity":100,"svgfill":"#ffb3c1"},{"id":"7kki13vJ","type":"svg","url":"userAsset:d53cb250-dc2d-4d22-a159-5ab4a8fd2d6d.svg","mediaName":"Cross.svg","width":40,"height":40,"x":0,"y":600,"angle":0,"scale":1,"opacity":100,"svgfill":"#ffb3c1"},{"id":"NXntcE2P","type":"svg","url":"userAsset:d53cb250-dc2d-4d22-a159-5ab4a8fd2d6d.svg","mediaName":"Cross.svg","width":40,"height":40,"x":0,"y":400,"angle":0,"scale":1,"opacity":100,"svgfill":"#ffb3c1"},{"id":"zdbqik3r","type":"svg","url":"userAsset:d53cb250-dc2d-4d22-a159-5ab4a8fd2d6d.svg","mediaName":"Cross.svg","width":40,"height":40,"x":0,"y":200,"angle":0,"scale":1,"opacity":100,"svgfill":"#ffb3c1"},{"id":"cOrJXwtb","type":"svg","url":"userAsset:d53cb250-dc2d-4d22-a159-5ab4a8fd2d6d.svg","mediaName":"Cross.svg","width":40,"height":40,"x":0,"y":0,"angle":0,"scale":1,"opacity":100,"svgfill":"#ffb3c1"}],"scale":1,"angle":0,"opacity":100,"id":"hlbzBZBO","type":"layerGrp","x":738.3717146330935,"y":12.792934171000445,"width":40,"height":1040,"cornerRadius":0,"name":"Column"},{"layers":[{"id":"ZObeIPJX","type":"svg","url":"userAsset:d53cb250-dc2d-4d22-a159-5ab4a8fd2d6d.svg","mediaName":"Cross.svg","width":40,"height":40,"x":0,"y":800,"angle":0,"scale":1,"opacity":100,"svgfill":"#ffb3c1"},{"id":"VOr7d70N","type":"svg","url":"userAsset:d53cb250-dc2d-4d22-a159-5ab4a8fd2d6d.svg","mediaName":"Cross.svg","width":40,"height":40,"x":0,"y":600,"angle":0,"scale":1,"opacity":100,"svgfill":"#ffb3c1"},{"id":"MrOrn9Ji","type":"svg","url":"userAsset:d53cb250-dc2d-4d22-a159-5ab4a8fd2d6d.svg","mediaName":"Cross.svg","width":40,"height":40,"x":0,"y":400,"angle":0,"scale":1,"opacity":100,"svgfill":"#ffb3c1"},{"id":"zxNxMF7y","type":"svg","url":"userAsset:d53cb250-dc2d-4d22-a159-5ab4a8fd2d6d.svg","mediaName":"Cross.svg","width":40,"height":40,"x":0,"y":200,"angle":0,"scale":1,"opacity":100,"svgfill":"#ffb3c1"},{"id":"W73Cxk4a","type":"svg","url":"userAsset:d53cb250-dc2d-4d22-a159-5ab4a8fd2d6d.svg","mediaName":"Cross.svg","width":40,"height":40,"x":0,"y":0,"angle":0,"scale":1,"opacity":100,"svgfill":"#ffb3c1"}],"scale":1,"angle":0,"opacity":100,"id":"gP7bur7n","type":"layerGrp","x":937,"y":117,"width":40,"height":840,"cornerRadius":0,"name":"Column"},{"layers":[{"id":"CVxvEBgh","type":"svg","url":"userAsset:d53cb250-dc2d-4d22-a159-5ab4a8fd2d6d.svg","mediaName":"Cross.svg","width":40,"height":40,"x":0,"y":1000,"angle":0,"scale":1,"opacity":100,"svgfill":"#ffb3c1"},{"id":"STIgL9KH","type":"svg","url":"userAsset:d53cb250-dc2d-4d22-a159-5ab4a8fd2d6d.svg","mediaName":"Cross.svg","width":40,"height":40,"x":0,"y":800,"angle":0,"scale":1,"opacity":100,"svgfill":"#ffb3c1"},{"id":"lrbf9RKh","type":"svg","url":"userAsset:d53cb250-dc2d-4d22-a159-5ab4a8fd2d6d.svg","mediaName":"Cross.svg","width":40,"height":40,"x":0,"y":600,"angle":0,"scale":1,"opacity":100,"svgfill":"#ffb3c1"},{"id":"S6k93CDN","type":"svg","url":"userAsset:d53cb250-dc2d-4d22-a159-5ab4a8fd2d6d.svg","mediaName":"Cross.svg","width":40,"height":40,"x":0,"y":400,"angle":0,"scale":1,"opacity":100,"svgfill":"#ffb3c1"},{"id":"MmsC987M","type":"svg","url":"userAsset:d53cb250-dc2d-4d22-a159-5ab4a8fd2d6d.svg","mediaName":"Cross.svg","width":40,"height":40,"x":0,"y":200,"angle":0,"scale":1,"opacity":100,"svgfill":"#ffb3c1"},{"id":"7Ggr0dTd","type":"svg","url":"userAsset:d53cb250-dc2d-4d22-a159-5ab4a8fd2d6d.svg","mediaName":"Cross.svg","width":40,"height":40,"x":0,"y":0,"angle":0,"scale":1,"opacity":100,"svgfill":"#ffb3c1"}],"scale":1,"angle":0,"opacity":100,"id":"v56SAV1E","type":"layerGrp","x":1137.7041875233651,"y":16.99380148281432,"width":40,"height":1040,"cornerRadius":0,"name":"Column"},{"layers":[{"id":"n1bRb9C8","type":"svg","url":"userAsset:d53cb250-dc2d-4d22-a159-5ab4a8fd2d6d.svg","mediaName":"Cross.svg","width":40,"height":40,"x":0,"y":800,"angle":0,"scale":1,"opacity":100,"svgfill":"#ffb3c1"},{"id":"iAHioTUg","type":"svg","url":"userAsset:d53cb250-dc2d-4d22-a159-5ab4a8fd2d6d.svg","mediaName":"Cross.svg","width":40,"height":40,"x":0,"y":600,"angle":0,"scale":1,"opacity":100,"svgfill":"#ffb3c1"},{"id":"svGtaS1r","type":"svg","url":"userAsset:d53cb250-dc2d-4d22-a159-5ab4a8fd2d6d.svg","mediaName":"Cross.svg","width":40,"height":40,"x":0,"y":400,"angle":0,"scale":1,"opacity":100,"svgfill":"#ffb3c1"},{"id":"QMnnEeAf","type":"svg","url":"userAsset:d53cb250-dc2d-4d22-a159-5ab4a8fd2d6d.svg","mediaName":"Cross.svg","width":40,"height":40,"x":0,"y":200,"angle":0,"scale":1,"opacity":100,"svgfill":"#ffb3c1"},{"id":"I5iXa2rt","type":"svg","url":"userAsset:d53cb250-dc2d-4d22-a159-5ab4a8fd2d6d.svg","mediaName":"Cross.svg","width":40,"height":40,"x":0,"y":0,"angle":0,"scale":1,"opacity":100,"svgfill":"#ffb3c1"}],"scale":1,"angle":0,"opacity":100,"id":"BEtwfxHV","type":"layerGrp","x":1337.6675271097283,"y":112.79913268818612,"width":40,"height":840,"cornerRadius":0,"name":"Column"},{"layers":[{"id":"ANZagkSH","type":"svg","url":"userAsset:d53cb250-dc2d-4d22-a159-5ab4a8fd2d6d.svg","mediaName":"Cross.svg","width":40,"height":40,"x":0,"y":1000,"angle":0,"scale":1,"opacity":100,"svgfill":"#ffb3c1"},{"id":"nu3fBTdw","type":"svg","url":"userAsset:d53cb250-dc2d-4d22-a159-5ab4a8fd2d6d.svg","mediaName":"Cross.svg","width":40,"height":40,"x":0,"y":800,"angle":0,"scale":1,"opacity":100,"svgfill":"#ffb3c1"},{"id":"l7HM3uJZ","type":"svg","url":"userAsset:d53cb250-dc2d-4d22-a159-5ab4a8fd2d6d.svg","mediaName":"Cross.svg","width":40,"height":40,"x":0,"y":600,"angle":0,"scale":1,"opacity":100,"svgfill":"#ffb3c1"},{"id":"abWiRtV2","type":"svg","url":"userAsset:d53cb250-dc2d-4d22-a159-5ab4a8fd2d6d.svg","mediaName":"Cross.svg","width":40,"height":40,"x":0,"y":400,"angle":0,"scale":1,"opacity":100,"svgfill":"#ffb3c1"},{"id":"r36Lq2PC","type":"svg","url":"userAsset:d53cb250-dc2d-4d22-a159-5ab4a8fd2d6d.svg","mediaName":"Cross.svg","width":40,"height":40,"x":0,"y":200,"angle":0,"scale":1,"opacity":100,"svgfill":"#ffb3c1"},{"id":"oOesF2Xc","type":"svg","url":"userAsset:d53cb250-dc2d-4d22-a159-5ab4a8fd2d6d.svg","mediaName":"Cross.svg","width":40,"height":40,"x":0,"y":0,"angle":0,"scale":1,"opacity":100,"svgfill":"#ffb3c1"}],"scale":1,"angle":0,"opacity":100,"id":"Z63IVzzR","type":"layerGrp","x":1538.3717146330935,"y":12.792934171000445,"width":40,"height":1040,"cornerRadius":0,"name":"Column"},{"layers":[{"id":"W8IZNdZT","type":"svg","url":"userAsset:d53cb250-dc2d-4d22-a159-5ab4a8fd2d6d.svg","mediaName":"Cross.svg","width":40,"height":40,"x":0,"y":800,"angle":0,"scale":1,"opacity":100,"svgfill":"#ffb3c1"},{"id":"hX7OOQCN","type":"svg","url":"userAsset:d53cb250-dc2d-4d22-a159-5ab4a8fd2d6d.svg","mediaName":"Cross.svg","width":40,"height":40,"x":0,"y":600,"angle":0,"scale":1,"opacity":100,"svgfill":"#ffb3c1"},{"id":"90k3XOwC","type":"svg","url":"userAsset:d53cb250-dc2d-4d22-a159-5ab4a8fd2d6d.svg","mediaName":"Cross.svg","width":40,"height":40,"x":0,"y":400,"angle":0,"scale":1,"opacity":100,"svgfill":"#ffb3c1"},{"id":"dvdKbzd8","type":"svg","url":"userAsset:d53cb250-dc2d-4d22-a159-5ab4a8fd2d6d.svg","mediaName":"Cross.svg","width":40,"height":40,"x":0,"y":200,"angle":0,"scale":1,"opacity":100,"svgfill":"#ffb3c1"},{"id":"09y26HPS","type":"svg","url":"userAsset:d53cb250-dc2d-4d22-a159-5ab4a8fd2d6d.svg","mediaName":"Cross.svg","width":40,"height":40,"x":0,"y":0,"angle":0,"scale":1,"opacity":100,"svgfill":"#ffb3c1"}],"scale":1,"angle":0,"opacity":100,"id":"vp4hPhTH","type":"layerGrp","x":1738.3350542194567,"y":108.59826537637224,"width":40,"height":840,"cornerRadius":0,"name":"Column"},{"layers":[{"id":"9xROUvR6","type":"svg","url":"userAsset:d53cb250-dc2d-4d22-a159-5ab4a8fd2d6d.svg","mediaName":"Cross.svg","width":40,"height":40,"x":0,"y":1000,"angle":0,"scale":1,"opacity":100,"svgfill":"#ffb3c1"},{"id":"uTw0sSc5","type":"svg","url":"userAsset:d53cb250-dc2d-4d22-a159-5ab4a8fd2d6d.svg","mediaName":"Cross.svg","width":40,"height":40,"x":0,"y":800,"angle":0,"scale":1,"opacity":100,"svgfill":"#ffb3c1"},{"id":"rCUNaJzg","type":"svg","url":"userAsset:d53cb250-dc2d-4d22-a159-5ab4a8fd2d6d.svg","mediaName":"Cross.svg","width":40,"height":40,"x":0,"y":600,"angle":0,"scale":1,"opacity":100,"svgfill":"#ffb3c1"},{"id":"0aLzTJQ9","type":"svg","url":"userAsset:d53cb250-dc2d-4d22-a159-5ab4a8fd2d6d.svg","mediaName":"Cross.svg","width":40,"height":40,"x":0,"y":400,"angle":0,"scale":1,"opacity":100,"svgfill":"#ffb3c1"},{"id":"KUVTF4m2","type":"svg","url":"userAsset:d53cb250-dc2d-4d22-a159-5ab4a8fd2d6d.svg","mediaName":"Cross.svg","width":40,"height":40,"x":0,"y":200,"angle":0,"scale":1,"opacity":100,"svgfill":"#ffb3c1"},{"id":"8CdIolui","type":"svg","url":"userAsset:d53cb250-dc2d-4d22-a159-5ab4a8fd2d6d.svg","mediaName":"Cross.svg","width":40,"height":40,"x":0,"y":0,"angle":0,"scale":1,"opacity":100,"svgfill":"#ffb3c1"}],"scale":1,"angle":0,"opacity":100,"id":"htr9Tw92","type":"layerGrp","x":1939.0392417428218,"y":8.59206685918657,"width":40,"height":1040,"cornerRadius":0,"name":"Column"}],"operations":[{"id":"Pf88c0ai","type":"opGrp","operations":[{"toValue":90,"easing":"natural","type":"rotate","startTime":0,"targetId":"ZObeIPJX","id":"dbO41ODn","endTime":800},{"toValue":90,"easing":"natural","type":"rotate","startTime":0,"targetId":"MrOrn9Ji","id":"V23ckHQ2","endTime":800},{"toValue":90,"easing":"natural","type":"rotate","startTime":0,"targetId":"W73Cxk4a","id":"q4ssx03Q","endTime":800},{"toValue":-90,"easing":"natural","type":"rotate","startTime":0,"targetId":"VOr7d70N","id":"yvxnceak","endTime":800},{"toValue":-90,"easing":"natural","type":"rotate","startTime":0,"targetId":"zxNxMF7y","id":"G9fTPlVZ","endTime":800}],"name":"Column rotation"},{"id":"8SvEx81O","type":"opGrp","operations":[{"toValue":90,"easing":"natural","type":"rotate","startTime":0,"targetId":"MmsC987M","id":"5up5RNgP","endTime":800},{"toValue":90,"easing":"natural","type":"rotate","startTime":0,"targetId":"lrbf9RKh","id":"ybXnpEwR","endTime":800},{"toValue":90,"easing":"natural","type":"rotate","startTime":0,"targetId":"CVxvEBgh","id":"QNQdlETh","endTime":800},{"toValue":-90,"easing":"natural","type":"rotate","startTime":0,"targetId":"STIgL9KH","id":"RWc1DLOG","endTime":800},{"toValue":-90,"easing":"natural","type":"rotate","startTime":0,"targetId":"S6k93CDN","id":"aXysxVEC","endTime":800},{"toValue":-90,"easing":"natural","type":"rotate","startTime":0,"targetId":"7Ggr0dTd","id":"wDgnQLeD","endTime":800}],"name":"Column rotation"},{"id":"uo2tXOmk","type":"opGrp","operations":[{"toValue":-90,"easing":"natural","type":"rotate","startTime":0,"targetId":"n1bRb9C8","id":"3EMLuCrI","endTime":800},{"toValue":-90,"easing":"natural","type":"rotate","startTime":0,"targetId":"svGtaS1r","id":"EIQgkU9y","endTime":800},{"toValue":-90,"easing":"natural","type":"rotate","startTime":0,"targetId":"I5iXa2rt","id":"MovqPyXK","endTime":800},{"toValue":90,"easing":"natural","type":"rotate","startTime":0,"targetId":"iAHioTUg","id":"3sJ6pszW","endTime":800},{"toValue":90,"easing":"natural","type":"rotate","startTime":0,"targetId":"QMnnEeAf","id":"KE1oZsMc","endTime":800}],"name":"Column rotation"},{"id":"wpeOuKst","type":"opGrp","operations":[{"toValue":-90,"easing":"natural","type":"rotate","startTime":0,"targetId":"r36Lq2PC","id":"e3mwsTIW","endTime":800},{"toValue":-90,"easing":"natural","type":"rotate","startTime":0,"targetId":"l7HM3uJZ","id":"5wvBhAC8","endTime":800},{"toValue":-90,"easing":"natural","type":"rotate","startTime":0,"targetId":"ANZagkSH","id":"Myb75UTD","endTime":800},{"toValue":90,"easing":"natural","type":"rotate","startTime":0,"targetId":"nu3fBTdw","id":"cTxRE2kB","endTime":800},{"toValue":90,"easing":"natural","type":"rotate","startTime":0,"targetId":"abWiRtV2","id":"enDiknGp","endTime":800},{"toValue":90,"easing":"natural","type":"rotate","startTime":0,"targetId":"oOesF2Xc","id":"Po5VJh5M","endTime":800}],"name":"Column rotation"},{"id":"ZCyETVBW","type":"opGrp","operations":[{"toValue":90,"easing":"natural","type":"rotate","startTime":0,"targetId":"W8IZNdZT","id":"sC58wcg6","endTime":800},{"toValue":90,"easing":"natural","type":"rotate","startTime":0,"targetId":"90k3XOwC","id":"v9XtDNtV","endTime":800},{"toValue":90,"easing":"natural","type":"rotate","startTime":0,"targetId":"09y26HPS","id":"3664hGUH","endTime":800},{"toValue":-90,"easing":"natural","type":"rotate","startTime":0,"targetId":"hX7OOQCN","id":"qCTt3mvS","endTime":800},{"toValue":-90,"easing":"natural","type":"rotate","startTime":0,"targetId":"dvdKbzd8","id":"vO4KAt3q","endTime":800}],"name":"Column rotation"},{"id":"cfXLsBb3","type":"opGrp","operations":[{"toValue":90,"easing":"natural","type":"rotate","startTime":0,"targetId":"KUVTF4m2","id":"qSC260Fk","endTime":800},{"toValue":90,"easing":"natural","type":"rotate","startTime":0,"targetId":"rCUNaJzg","id":"Jfxwrdn2","endTime":800},{"toValue":90,"easing":"natural","type":"rotate","startTime":0,"targetId":"9xROUvR6","id":"2O4dcPIX","endTime":800},{"toValue":-90,"easing":"natural","type":"rotate","startTime":0,"targetId":"uTw0sSc5","id":"KIdG9KVR","endTime":800},{"toValue":-90,"easing":"natural","type":"rotate","startTime":0,"targetId":"0aLzTJQ9","id":"6Bxx2aPg","endTime":800},{"toValue":-90,"easing":"natural","type":"rotate","startTime":0,"targetId":"8CdIolui","id":"7oJtA3W8","endTime":800}],"name":"Column rotation"},{"id":"kzExSrPz","type":"opGrp","operations":[{"toValue":90,"easing":"natural","type":"rotate","startTime":0,"targetId":"UStNWFvS","id":"iTvyVIrf","endTime":800},{"toValue":90,"easing":"natural","type":"rotate","startTime":0,"targetId":"9GiNZPUd","id":"6lUJBkZt","endTime":800},{"toValue":90,"easing":"natural","type":"rotate","startTime":0,"targetId":"M9954U3h","id":"hPIXor4V","endTime":800},{"toValue":-90,"easing":"natural","type":"rotate","startTime":0,"targetId":"GoTxxbny","id":"9Z29QiyN","endTime":800},{"toValue":-90,"easing":"natural","type":"rotate","startTime":0,"targetId":"yoTD10dT","id":"gEblnFZ1","endTime":800}],"name":"Column rotation"},{"id":"BaGadRw3","type":"opGrp","operations":[{"toValue":90,"easing":"natural","type":"rotate","startTime":0,"targetId":"UzrRmrOF","id":"nLsydyRt","endTime":800},{"toValue":90,"easing":"natural","type":"rotate","startTime":0,"targetId":"RTsD9U3M","id":"VtotLQFK","endTime":800},{"toValue":90,"easing":"natural","type":"rotate","startTime":0,"targetId":"JJf0eJuX","id":"28l3apTB","endTime":800},{"toValue":-90,"easing":"natural","type":"rotate","startTime":0,"targetId":"1iPM8VNE","id":"xKBUoPUs","endTime":800},{"toValue":-90,"easing":"natural","type":"rotate","startTime":0,"targetId":"kp6Gwzr1","id":"GwrHEWQo","endTime":800},{"toValue":-90,"easing":"natural","type":"rotate","startTime":0,"targetId":"Sb0Zbd4M","id":"3JMkER3k","endTime":800}],"name":"Column rotation"},{"id":"8mqoDQqq","type":"opGrp","operations":[{"toValue":-90,"easing":"natural","type":"rotate","startTime":0,"targetId":"uB929Uzz","id":"XWSqfXwh","endTime":800},{"toValue":-90,"easing":"natural","type":"rotate","startTime":0,"targetId":"XVffq7KK","id":"a14CO0IH","endTime":800},{"toValue":-90,"easing":"natural","type":"rotate","startTime":0,"targetId":"H0qoSgAF","id":"74Vn9s7V","endTime":800},{"toValue":90,"easing":"natural","type":"rotate","startTime":0,"targetId":"kzsRoRVd","id":"m8r7NdEZ","endTime":800},{"toValue":90,"easing":"natural","type":"rotate","startTime":0,"targetId":"WLOx6oU2","id":"T1teHKF2","endTime":800}],"name":"Column rotation"},{"id":"t884ZM4W","type":"opGrp","operations":[{"toValue":-90,"easing":"natural","type":"rotate","startTime":0,"targetId":"zdbqik3r","id":"MN5CJ3RR","endTime":800},{"toValue":-90,"easing":"natural","type":"rotate","startTime":0,"targetId":"7kki13vJ","id":"oPnR6AdB","endTime":800},{"toValue":-90,"easing":"natural","type":"rotate","startTime":0,"targetId":"VF9i6mBw","id":"FIzduT5t","endTime":800},{"toValue":90,"easing":"natural","type":"rotate","startTime":0,"targetId":"c3D5rgI3","id":"B9JiOgvL","endTime":800},{"toValue":90,"easing":"natural","type":"rotate","startTime":0,"targetId":"NXntcE2P","id":"ue895vFe","endTime":800},{"toValue":90,"easing":"natural","type":"rotate","startTime":0,"targetId":"cOrJXwtb","id":"D1kciWVc","endTime":800}],"name":"Column rotation"}],"id":"QZgqtyMO"}]},"syncedAt":"2022-04-01T13:24:07.063Z","createdAt":"2021-12-13T15:27:54.607Z"}