{"name":"Animated iPad mockup","conf":{"version":12,"artboards":[{"id":"466:392","item":{"angle":0,"scale":1,"opacity":100,"shadowEnabled":false,"type":"artboard","name":"Scene","mirrorX":false,"mirrorY":false,"x":14256,"y":762,"width":1600,"height":1200,"isHidden":false,"cornerRadius":0,"clipsContent":true,"background":true,"fillColor":"#17082C","duration":8000},"children":[{"id":"sG4frm4dJByHxnHlJSqQm","item":{"type":"operationsTree"},"children":[{"id":"9hVoOdwC73wTuQs6_o-DY","item":{"type":"opGrp","name":"Grid – Scale in"},"children":[{"id":"4XpJa8TWeKimxM-GtGw3-","item":{"toValue":2,"easing":{"name":"natural"},"type":"scale","startTime":0,"targetId":"8h3jPAZKk3Rk4LKRzIdi1","endTime":1500}},{"id":"Iz2ZQ3hbBwVD_tQA_by0F","item":{"colorSpace":"rgb","toValue":"#F0F9FF","easing":{"name":"natural"},"type":"color","startTime":0,"targetId":"466:392","endTime":1500}},{"id":"K1iYYNszL07oflcbksSoQ","item":{"easing":{"name":"linear"},"type":"fadeIn","startTime":599,"targetId":"wtoVkhGRFpLbJ-hraeG4e","endTime":1280}}]},{"id":"RAaWoskmfaAyVcuAqnsvO","item":{"type":"opGrp","name":"Screens slide"},"children":[{"id":"CtZJGt21nRpzsTAeouSRo","item":{"easing":{"name":"natural"},"direction":"down","padding":0,"type":"maskSlideOut","startTime":1000,"targetId":"B27iVeH7IHZu1yDFS4b9V","endTime":2500}},{"id":"jxGwvxzhBJbxeu2WO9EIG","item":{"direction":"down","padding":0,"easing":{"name":"natural"},"type":"maskSlideIn","startTime":1000,"targetId":"huKv-WDkQRJFOZfjbwUBc","endTime":2500}},{"id":"g1B7qQlu69D4iM40SuHjf","item":{"toValue":{"moveX":0,"moveY":860},"easing":{"name":"natural"},"type":"move","startTime":1000,"targetId":"wtoVkhGRFpLbJ-hraeG4e","endTime":2500}},{"id":"CkFZWacSdBByAlzJgeWA0","item":{"easing":{"name":"natural"},"direction":"down","padding":0,"type":"maskSlideOut","startTime":2500,"targetId":"huKv-WDkQRJFOZfjbwUBc","endTime":4000}},{"id":"PF6JaIFVAoVQ2p7dpWld2","item":{"direction":"down","padding":0,"easing":{"name":"natural"},"type":"maskSlideIn","startTime":2500,"targetId":"SGUrsmT2NIVUDVwiQn9V1","endTime":4000}},{"id":"jbTjfEiBCZHFeHNasHut9","item":{"toValue":{"moveX":0,"moveY":860},"easing":{"name":"natural"},"type":"move","startTime":2500,"targetId":"wtoVkhGRFpLbJ-hraeG4e","endTime":4000}},{"id":"Rvz0dW1QJTaNqwkvw2YSi","item":{"direction":"down","padding":0,"easing":{"name":"natural"},"type":"maskSlideIn","startTime":4000,"targetId":"naE-GFzfQjmr3HMewi6uG","endTime":5500}},{"id":"AsHM8d9FMyKYM9WIfhkWi","item":{"easing":{"name":"natural"},"direction":"down","padding":0,"type":"maskSlideOut","startTime":3999,"targetId":"SGUrsmT2NIVUDVwiQn9V1","endTime":5499}},{"id":"hd09vEBmNt9AOJv_J2-IL","item":{"toValue":{"moveX":0,"moveY":860},"easing":{"name":"natural"},"type":"move","startTime":4000,"targetId":"wtoVkhGRFpLbJ-hraeG4e","endTime":5500}},{"id":"457GrWhXqC2IC3xrGADDK","item":{"easing":{"name":"natural"},"direction":"down","padding":0,"type":"maskSlideOut","startTime":5500,"targetId":"naE-GFzfQjmr3HMewi6uG","endTime":7000}},{"id":"H5UWDbnN9y3CL8NBSp3l8","item":{"direction":"down","padding":0,"easing":{"name":"natural"},"type":"maskSlideIn","startTime":5500,"targetId":"BblMBOto2slGm1H0FHiaQ","endTime":7000}},{"id":"bJzSstXCgiO8LKSAc9q14","item":{"toValue":{"moveX":0,"moveY":860},"easing":{"name":"natural"},"type":"move","startTime":5500,"targetId":"wtoVkhGRFpLbJ-hraeG4e","endTime":7000}}]},{"id":"gAz7K7lKrXLRTyzHHY3A-","item":{"type":"opGrp","name":"Grid – Scale out"},"children":[{"id":"HJjMqWHOmtDsuN422Qntr","item":{"toValue":1,"easing":{"name":"natural"},"type":"scale","startTime":6800,"targetId":"8h3jPAZKk3Rk4LKRzIdi1","endTime":8000}},{"id":"Ouf0KCoE6owHm5OcpzUYa","item":{"colorSpace":"rgb","toValue":"#17082C","easing":{"name":"natural"},"type":"color","startTime":6800,"targetId":"466:392","endTime":8000}},{"id":"jQGRWz6TDno0qRoAX_ONg","item":{"easing":{"name":"linear"},"type":"fadeOut","startTime":6800,"targetId":"wtoVkhGRFpLbJ-hraeG4e","endTime":7000}}]}]},{"id":"jU_SfYE5DQ-8ATSBawxzK","item":{"type":"layersTree"},"children":[{"id":"wtoVkhGRFpLbJ-hraeG4e","item":{"opacity":100,"scale":1,"angle":0,"shadowEnabled":false,"x":340,"y":280,"width":920,"height":640,"type":"layerGrp","cornerRadius":0,"clipsContent":false,"background":false,"strokeEnabled":false,"name":"Slider","isHidden":false},"children":[{"id":"wcMVgSapZNrWLWRipVlp4","item":{"type":"image","url":"https://d154zarmrcpu4a.cloudfront.net/XDNx0LTxX18WLyD1yunW4.jpg","mediaName":"white-2.jpg","width":920,"height":640,"x":0,"y":-4300,"cornerRadius":0,"shadowEnabled":false,"strokeEnabled":false,"angle":0,"scale":1,"opacity":100,"name":"Screen 06"}},{"id":"wGys9ueQwDTKFb0SN1BIj","item":{"type":"image","url":"https://d154zarmrcpu4a.cloudfront.net/3AyM45Qg7nCRAChKXCi5C.jpg","mediaName":"blue.jpg","width":920,"height":640,"x":0,"y":-3440,"cornerRadius":0,"shadowEnabled":false,"strokeEnabled":false,"angle":0,"scale":1,"opacity":100,"name":"Screen 05","isHidden":false}},{"id":"cX-Fnf-mpioZnMcfd0Hr2","item":{"type":"image","url":"https://d154zarmrcpu4a.cloudfront.net/stmVpl1hW58it8P3BZb9e.jpg","mediaName":"white-2.jpg","width":920,"height":640,"x":0,"y":-2580,"cornerRadius":0,"shadowEnabled":false,"strokeEnabled":false,"angle":0,"scale":1,"opacity":100,"name":"Screen 04"}},{"id":"--LgeODNEIHppLbT0kOq5","item":{"type":"image","url":"https://d154zarmrcpu4a.cloudfront.net/_YhQ94CWETqoPyDfBTa9Z.jpg","mediaName":"pastel-2.jpg","width":920,"height":640,"x":0,"y":-1720,"cornerRadius":0,"shadowEnabled":false,"strokeEnabled":false,"angle":0,"scale":1,"opacity":100,"name":"Screen 03"}},{"id":"YknvwTFKZPFKE6eAtS8PL","item":{"type":"image","url":"https://d154zarmrcpu4a.cloudfront.net/3AyM45Qg7nCRAChKXCi5C.jpg","mediaName":"blue.jpg","width":920,"height":640,"x":0,"y":-860,"cornerRadius":0,"shadowEnabled":false,"strokeEnabled":false,"angle":0,"scale":1,"opacity":100,"name":"Screen 02","isHidden":false}},{"id":"hj2hlW6rFhCcSWD65dpab","item":{"type":"image","url":"https://d154zarmrcpu4a.cloudfront.net/XDNx0LTxX18WLyD1yunW4.jpg","mediaName":"white-2.jpg","width":920,"height":640,"x":0,"y":0,"cornerRadius":0,"shadowEnabled":false,"strokeEnabled":false,"angle":0,"scale":1,"opacity":100,"name":"Screen 01"}},{"id":"YdYccD3WlNysBNEvRcjFr","item":{"type":"image","url":"https://d154zarmrcpu4a.cloudfront.net/3AyM45Qg7nCRAChKXCi5C.jpg","mediaName":"blue.jpg","width":920,"height":640,"x":0,"y":860,"cornerRadius":0,"shadowEnabled":false,"strokeEnabled":false,"angle":0,"scale":1,"opacity":100,"name":"Screen 00","isHidden":false}}]},{"id":"8h3jPAZKk3Rk4LKRzIdi1","item":{"opacity":100,"scale":1,"angle":0,"shadowEnabled":false,"x":0,"y":0,"width":1600,"height":1200,"type":"layerGrp","cornerRadius":0,"clipsContent":false,"background":false,"strokeEnabled":false,"name":"Grid","isHidden":false},"children":[{"id":"E5CpkUVLGIDm_rIn52VSg","item":{"opacity":100,"scale":1,"angle":0,"shadowEnabled":false,"x":1281,"y":991,"width":662,"height":482,"type":"layerGrp","cornerRadius":0,"clipsContent":false,"background":false,"strokeEnabled":false,"name":"Device 09","isHidden":false},"children":[{"id":"cVOlLW1RVDKzsat-auKn_","item":{"type":"image","url":"https://d154zarmrcpu4a.cloudfront.net/-tPipW8OaFJIf8Im8yzMf.jpg","mediaName":"white.jpg","width":592,"height":412,"x":35,"y":35,"cornerRadius":0,"shadowEnabled":false,"strokeEnabled":false,"angle":0,"scale":1,"opacity":100,"name":"Media"}},{"id":"TDi61OxDAlcbDUHlZiHB4","item":{"type":"image","url":"https://d154zarmrcpu4a.cloudfront.net/d6ca5b07-008f-40b0-9419-56b05f1da25f.png","mediaName":"iPad Air - Space Gray - Landscape.png","width":662,"height":482,"x":0,"y":0,"cornerRadius":0,"shadowEnabled":false,"strokeEnabled":false,"angle":0,"scale":1,"opacity":100,"name":"iPad Air – Bezel"}}]},{"id":"e4N3kqTG9s2jzqqeEtw38","item":{"opacity":100,"scale":1,"angle":0,"shadowEnabled":false,"x":469,"y":991,"width":662,"height":482,"type":"layerGrp","cornerRadius":0,"clipsContent":false,"background":false,"strokeEnabled":false,"name":"Device 08","isHidden":false},"children":[{"id":"FI3CcX6nR0o4KITgWhHaX","item":{"type":"image","url":"https://d154zarmrcpu4a.cloudfront.net/RkfkRDDd2NYX3Ec4jMUwf.jpg","mediaName":"blue.jpg","width":592,"height":412,"x":35,"y":35,"cornerRadius":0,"shadowEnabled":false,"strokeEnabled":false,"angle":0,"scale":1,"opacity":100,"name":"Media"}},{"id":"gk38WrIldC2g3rmFKXu9s","item":{"type":"image","url":"https://d154zarmrcpu4a.cloudfront.net/d6ca5b07-008f-40b0-9419-56b05f1da25f.png","mediaName":"iPad Air - Space Gray - Landscape.png","width":662,"height":482,"x":0,"y":0,"cornerRadius":0,"shadowEnabled":false,"strokeEnabled":false,"angle":0,"scale":1,"opacity":100,"name":"iPad Air – Bezel"}}]},{"id":"8zCnXBCuLC8RStTFMiKI3","item":{"opacity":100,"scale":1,"angle":0,"shadowEnabled":false,"x":-343,"y":991,"width":662,"height":482,"type":"layerGrp","cornerRadius":0,"clipsContent":false,"background":false,"strokeEnabled":false,"name":"Device 07","isHidden":false},"children":[{"id":"5O2J9_WbCqFJtPzAhvWAb","item":{"type":"image","url":"https://d154zarmrcpu4a.cloudfront.net/Zf1I18dnofFFJzCHm52j_.jpg","mediaName":"white.jpg","width":592,"height":412,"x":35,"y":35,"cornerRadius":0,"shadowEnabled":false,"strokeEnabled":false,"angle":0,"scale":1,"opacity":100,"name":"Media"}},{"id":"FDoBKK1Uzl4eohTtcwWO9","item":{"type":"image","url":"https://d154zarmrcpu4a.cloudfront.net/d6ca5b07-008f-40b0-9419-56b05f1da25f.png","mediaName":"iPad Air - Space Gray - Landscape.png","width":662,"height":482,"x":0,"y":0,"cornerRadius":0,"shadowEnabled":false,"strokeEnabled":false,"angle":0,"scale":1,"opacity":100,"name":"iPad Air – Bezel"}}]},{"id":"Z0LrfetilBN5ccCWZQItn","item":{"opacity":100,"scale":1,"angle":0,"shadowEnabled":false,"x":1281,"y":359,"width":662,"height":482,"type":"layerGrp","cornerRadius":0,"clipsContent":false,"background":false,"strokeEnabled":false,"name":"Device 06","isHidden":false},"children":[{"id":"sfL1MEYyu-qvr4OBzmB99","item":{"type":"image","url":"https://d154zarmrcpu4a.cloudfront.net/afzqZkX-og5EdHivKZy3f.jpg","mediaName":"pastel.jpg","width":592,"height":412,"x":35,"y":35,"cornerRadius":0,"shadowEnabled":false,"strokeEnabled":false,"angle":0,"scale":1,"opacity":100,"name":"Media"}},{"id":"V3kdeBQqPDc25n163AijG","item":{"type":"image","url":"https://d154zarmrcpu4a.cloudfront.net/d6ca5b07-008f-40b0-9419-56b05f1da25f.png","mediaName":"iPad Air - Space Gray - Landscape.png","width":662,"height":482,"x":0,"y":0,"cornerRadius":0,"shadowEnabled":false,"strokeEnabled":false,"angle":0,"scale":1,"opacity":100,"name":"iPad Air – Bezel"}}]},{"id":"nS-VfyyjzFwW3fN26sWIj","item":{"opacity":100,"scale":1,"angle":0,"shadowEnabled":false,"x":469,"y":359,"width":662,"height":482,"type":"layerGrp","cornerRadius":0,"clipsContent":false,"background":false,"strokeEnabled":false,"name":"Device 05"},"children":[{"id":"CHWklzcVP8n8tyKIEpwx_","item":{"opacity":100,"scale":1,"angle":0,"shadowEnabled":false,"x":35,"y":35,"width":592,"height":412,"type":"layerGrp","cornerRadius":0,"clipsContent":true,"background":false,"strokeEnabled":false,"name":"Media container"},"children":[{"id":"BblMBOto2slGm1H0FHiaQ","item":{"type":"image","url":"https://d154zarmrcpu4a.cloudfront.net/T0CHhKrnbdclPfKoaVCOQ.jpg","mediaName":"blue.jpg","width":592,"height":412,"x":0,"y":0,"cornerRadius":0,"shadowEnabled":false,"strokeEnabled":false,"angle":0,"scale":1,"opacity":100,"isHidden":false,"name":"Screen 05"}},{"id":"naE-GFzfQjmr3HMewi6uG","item":{"type":"image","url":"https://d154zarmrcpu4a.cloudfront.net/GXLk3Q3zRCWYiRoPrsqEK.jpg","mediaName":"white-2.jpg","width":592,"height":412,"x":0,"y":0,"cornerRadius":0,"shadowEnabled":false,"strokeEnabled":false,"angle":0,"scale":1,"opacity":100,"isHidden":false,"name":"Screen 04"}},{"id":"SGUrsmT2NIVUDVwiQn9V1","item":{"type":"image","url":"https://d154zarmrcpu4a.cloudfront.net/-5mtFKK6xXTut4kncy7xn.jpg","mediaName":"pastel-2.jpg","width":592,"height":412,"x":0,"y":0,"cornerRadius":0,"shadowEnabled":false,"strokeEnabled":false,"angle":0,"scale":1,"opacity":100,"isHidden":false,"name":"Screen 03"}},{"id":"huKv-WDkQRJFOZfjbwUBc","item":{"type":"image","url":"https://d154zarmrcpu4a.cloudfront.net/HWupiOOrumixnQUq5OejZ.jpg","mediaName":"blue.jpg","width":592,"height":412,"x":0,"y":0,"cornerRadius":0,"shadowEnabled":false,"strokeEnabled":false,"angle":0,"scale":1,"opacity":100,"isHidden":false,"name":"Screen 02"}},{"id":"B27iVeH7IHZu1yDFS4b9V","item":{"type":"image","url":"https://d154zarmrcpu4a.cloudfront.net/Qj34KsCo73j7mXp5TFVjZ.jpg","mediaName":"1180x820.jpg","width":592,"height":412,"x":0,"y":0,"cornerRadius":0,"shadowEnabled":false,"strokeEnabled":false,"angle":0,"scale":1,"opacity":100,"isHidden":false,"name":"Screen 01"}}]},{"id":"LdJzlhGrFuk5OG_4RRnHx","item":{"type":"image","url":"https://d154zarmrcpu4a.cloudfront.net/d6ca5b07-008f-40b0-9419-56b05f1da25f.png","mediaName":"iPad Air - Space Gray - Landscape.png","width":662,"height":482,"x":0,"y":0,"cornerRadius":0,"shadowEnabled":false,"strokeEnabled":false,"angle":0,"scale":1,"opacity":100,"name":"iPad Air – Bezel"}}]},{"id":"PcpeY2V3w2h4VZZ9Pysh5","item":{"opacity":100,"scale":1,"angle":0,"shadowEnabled":false,"x":-343,"y":359,"width":662,"height":482,"type":"layerGrp","cornerRadius":0,"clipsContent":false,"background":false,"strokeEnabled":false,"name":"Device 04","isHidden":false},"children":[{"id":"86R0YhuE4BqKwQ2UH3Ubx","item":{"type":"image","url":"https://d154zarmrcpu4a.cloudfront.net/vZYVBXXc0QWmOgx9Lar91.jpg","mediaName":"pastel.jpg","width":592,"height":412,"x":35,"y":35,"cornerRadius":0,"shadowEnabled":false,"strokeEnabled":false,"angle":0,"scale":1,"opacity":100,"name":"Media"}},{"id":"2I8bWfv7fzJkvHawq3Nw_","item":{"type":"image","url":"https://d154zarmrcpu4a.cloudfront.net/d6ca5b07-008f-40b0-9419-56b05f1da25f.png","mediaName":"iPad Air - Space Gray - Landscape.png","width":662,"height":482,"x":0,"y":0,"cornerRadius":0,"shadowEnabled":false,"strokeEnabled":false,"angle":0,"scale":1,"opacity":100,"name":"iPad Air – Bezel"}}]},{"id":"DRfFfB5uszwmlGDPCwIEN","item":{"opacity":100,"scale":1,"angle":0,"shadowEnabled":false,"x":1281,"y":-273,"width":662,"height":482,"type":"layerGrp","cornerRadius":0,"clipsContent":false,"background":false,"strokeEnabled":false,"name":"Device 03","isHidden":false},"children":[{"id":"QLTzBkERa9-5or6jEspBr","item":{"type":"image","url":"https://d154zarmrcpu4a.cloudfront.net/T8AsJrrLMEgJcZBsaQkca.jpg","mediaName":"white.jpg","width":592,"height":412,"x":35,"y":35,"cornerRadius":0,"shadowEnabled":false,"strokeEnabled":false,"angle":0,"scale":1,"opacity":100,"name":"Media"}},{"id":"kLd5hmMA8G3CXUnNrZemr","item":{"type":"image","url":"https://d154zarmrcpu4a.cloudfront.net/d6ca5b07-008f-40b0-9419-56b05f1da25f.png","mediaName":"iPad Air - Space Gray - Landscape.png","width":662,"height":482,"x":0,"y":0,"cornerRadius":0,"shadowEnabled":false,"strokeEnabled":false,"angle":0,"scale":1,"opacity":100,"name":"iPad Air – Bezel"}}]},{"id":"5b1nHEQjBuMKhkmob8xoh","item":{"opacity":100,"scale":1,"angle":0,"shadowEnabled":false,"x":469,"y":-273,"width":662,"height":482,"type":"layerGrp","cornerRadius":0,"clipsContent":false,"background":false,"strokeEnabled":false,"name":"Device 02","isHidden":false},"children":[{"id":"5RWcC8_LaJr-eZufY0WHf","item":{"type":"image","url":"https://d154zarmrcpu4a.cloudfront.net/TcEiB2G1UwKZ4LE5Zf2Fd.jpg","mediaName":"blue.jpg","width":592,"height":412,"x":35,"y":35,"cornerRadius":0,"shadowEnabled":false,"strokeEnabled":false,"angle":0,"scale":1,"opacity":100,"name":"Media"}},{"id":"8SEtH4qf0D4UL5U9yHupE","item":{"type":"image","url":"https://d154zarmrcpu4a.cloudfront.net/d6ca5b07-008f-40b0-9419-56b05f1da25f.png","mediaName":"iPad Air - Space Gray - Landscape.png","width":662,"height":482,"x":0,"y":0,"cornerRadius":0,"shadowEnabled":false,"strokeEnabled":false,"angle":0,"scale":1,"opacity":100,"name":"iPad Air – Bezel"}}]},{"id":"fqmlssb8Io-RgRTaEftzr","item":{"opacity":100,"scale":1,"angle":0,"shadowEnabled":false,"x":-343,"y":-273,"width":662,"height":482,"type":"layerGrp","cornerRadius":0,"clipsContent":false,"background":false,"strokeEnabled":false,"name":"Device 01","isHidden":false},"children":[{"id":"bAkZ10ybGtoPfe8pDgqxE","item":{"type":"image","url":"https://d154zarmrcpu4a.cloudfront.net/s6fGZZhtpMYdRKol1Lxp5.jpg","mediaName":"white.jpg","width":592,"height":412,"x":35,"y":35,"cornerRadius":0,"shadowEnabled":false,"strokeEnabled":false,"angle":0,"scale":1,"opacity":100,"name":"Media"}},{"id":"W9pwnXDDGw_AeSvwPGrZe","item":{"type":"image","url":"https://d154zarmrcpu4a.cloudfront.net/d6ca5b07-008f-40b0-9419-56b05f1da25f.png","mediaName":"iPad Air - Space Gray - Landscape.png","width":662,"height":482,"x":0,"y":0,"cornerRadius":0,"shadowEnabled":false,"strokeEnabled":false,"angle":0,"scale":1,"opacity":100,"name":"iPad Air – Bezel"}}]}]}]}]}],"ownerId":"68724143-b4d4-4f86","imported":{"from":"figma","id":"fngm4i86u3","device":"dvls57szh9","clientId":"5db945d2-7688-4b7c-b6d2-4dee6c3ea5ce","timestamp":1679932170846}},"syncedAt":"2023-05-30T15:36:01.698Z","createdAt":"2023-05-16T18:33:12.623Z"}